pi74HC595/__init__.py
pi74HC595/pi74HC595.py
pi74HC595-1.2.3.dist-info/LICENSE
pi74HC595-1.2.3.dist-info/METADATA
pi74HC595-1.2.3.dist-info/WHEEL
pi74HC595-1.2.3.dist-info/top_level.txt
pi74HC595-1.2.3.dist-info/RECORD
