Metadata-Version: 2.1
Name: pi74HC595
Version: 1.2.3
Summary: Use the 74HC595 Shift Register with a Raspberry Pi
Home-page: https://github.com/2kofawsome/pi74HC595
Author: Sam Gunter
Author-email: samgunter12@gmail.com
License: MIT
Keywords: Raspberry Pi GPIO 74HC595
Platform: UNKNOWN
Classifier: Programming Language :: Python :: 3
Classifier: Operating System :: POSIX :: Linux
Classifier: License :: OSI Approved :: MIT License
Classifier: Development Status :: 5 - Production/Stable
